<?xml version="1.0" encoding="UTF-8"?>
<alpino_adt version="1.3">
  <node cat="top" id="0" rel="top">
    <node cat="du" id="1" rel="--">
      <node cat="smain" id="2" rel="dp">
        <node cat="cp" id="3" rel="mod">
          <node id="4" pos="comp" rel="cmp" root="als" sc="als" sense="als"/>
          <node cat="ssub" id="5" rel="body">
            <node cat="np" id="6" rel="su">
              <node id="7" infl="de" pos="det" rel="det" root="de" sense="de"/>
              <node aform="base" id="8" infl="e" pos="adj" rel="mod" root="katholiek" sense="katholiek" vform="adj"/>
              <node gen="both" id="9" num="both" pos="noun" rel="hd" root="topturners(sters)" sense="topturners(sters)"/>
            </node>
            <node cat="pp" id="10" rel="mod">
              <node id="11" pos="prep" rel="hd" root="met" sense="met"/>
              <node cat="np" id="12" rel="obj1">
                <node id="13" infl="onze" pos="det" rel="det" root="ons" sense="ons"/>
                <node gen="de" id="14" num="sg" pos="noun" rel="hd" root="top" sense="top"/>
              </node>
            </node>
            <node cat="np" id="15" rel="obj1">
              <node id="16" infl="een" pos="det" rel="det" root="een" sense="een"/>
              <node gen="de" id="17" num="sg" pos="noun" rel="hd" root="ploeg" sense="ploeg"/>
            </node>
            <node id="18" infl="pl" pos="verb" rel="hd" root="vorm" sc="transitive" sense="vorm" tense="present"/>
          </node>
        </node>
        <node id="19" infl="sg3" pos="verb" rel="hd" root="maak" sc="ap_copula" sense="maak" tense="present"/>
        <node cat="np" id="20" rel="su">
          <node id="21" infl="de" pos="det" rel="det" root="de" sense="de"/>
          <node gen="both" id="22" num="both" pos="noun" rel="hd" root="nkgb" sense="nkgb"/>
        </node>
        <node aform="base" id="23" infl="no_e" pos="adj" rel="predc" root="confessioneel" sense="confessioneel" vform="adj"/>
      </node>
      <node cat="np" id="24" rel="dp">
        <node id="25" infl="geen" pos="det" rel="det" root="geen" sense="geen" wh="nwh"/>
        <node gen="het" id="26" num="sg" pos="noun" rel="hd" root="bezwaar" sense="bezwaar"/>
      </node>
    </node>
  </node>
</alpino_adt>
