<?xml version="1.0" encoding="UTF-8"?>
<alpino_adt version="1.3">
  <node cat="top" id="0" rel="top">
    <node cat="smain" id="1" rel="--">
      <node cat="np" id="2" rel="su">
        <node gen="de" id="3" num="sg" pos="noun" rel="hd" root="Theater_directeur" sense="Theater_directeur"/>
        <node cat="mwu" id="4" mwu_root="Werner Dueggelin" mwu_sense="Werner Dueggelin" rel="app">
          <node id="5" neclass="PER" num="both" pos="name" rel="mwp" root="Werner" sense="Werner"/>
          <node id="6" neclass="PER" num="both" pos="name" rel="mwp" root="Dueggelin" sense="Dueggelin"/>
        </node>
      </node>
      <node id="7" infl="sg" pos="verb" rel="hd" root="spreek" sc="transitive" sense="spreek" tense="past"/>
      <node cat="pp" id="8" rel="mod">
        <node id="9" pos="prep" rel="hd" root="achter" sense="achter"/>
        <node cat="np" id="10" rel="obj1">
          <node id="11" infl="de" pos="det" rel="det" root="de" sense="de"/>
          <node gen="de" id="12" num="pl" pos="noun" rel="hd" root="coulisse" sense="coulisse"/>
        </node>
      </node>
      <node cat="np" id="13" rel="obj1">
        <node id="14" infl="de" pos="det" rel="det" root="de" sense="de"/>
        <node gen="de" id="15" num="sg" pos="noun" rel="hd" root="tekst" sense="tekst"/>
      </node>
    </node>
  </node>
</alpino_adt>
