<?xml version="1.0" encoding="UTF-8"?>
<alpino_adt version="1.3">
  <node cat="top" id="0" rel="top">
    <node cat="smain" id="1" rel="--">
      <node case="nom" def="def" gen="de" id="2" index="1" num="sg" per="thi" pos="pron" rel="su" root="hij" sense="hij" wh="nwh"/>
      <node id="3" infl="sg" pos="verb" rel="hd" root="zal" sc="aux(inf)" sense="zal" tense="past"/>
      <node cat="inf" id="4" rel="vc">
        <node id="5" index="1" rel="su"/>
        <node id="6" infl="inf" pos="verb" rel="hd" root="moet" sc="modifier(aux(inf))" sense="moet"/>
        <node cat="inf" id="7" rel="vc">
          <node id="8" index="1" rel="su"/>
          <node cat="ppart" id="9" rel="vc">
            <node id="10" index="1" rel="su"/>
            <node id="11" pos="adv" rel="ld" root="daar" sense="daar" special="er_loc"/>
            <node cat="mwu" id="12" mwu_root="15 augustus" mwu_sense="15 augustus" rel="mod">
              <node id="13" pos="noun" rel="mwp" root="15" sense="15" special="tmp"/>
              <node id="14" pos="noun" rel="mwp" root="augustus" sense="augustus" special="tmp"/>
            </node>
            <node id="15" infl="psp" pos="verb" rel="hd" root="ben" sc="ld_adv" sense="ben"/>
          </node>
          <node id="16" infl="inf" pos="verb" rel="hd" root="ben" sc="aux_psp_zijn" sense="ben"/>
        </node>
      </node>
    </node>
  </node>
</alpino_adt>
