<?xml version="1.0" encoding="UTF-8"?>
<alpino_adt version="1.3">
  <node cat="top" id="0" rel="top">
    <node cat="du" id="1" rel="--">
      <node id="2" pos="comp" rel="dlink" root="maar" sc="root" sense="maar"/>
      <node cat="smain" id="3" rel="nucl">
        <node id="4" infl="het" pos="det" rel="su" root="dat" sense="dat" wh="nwh"/>
        <node id="5" infl="sg3" pos="verb" rel="hd" root="impliceer" sc="transitive" sense="impliceer" tense="present"/>
        <node id="6" pos="adv" rel="mod" root="nog" sense="nog"/>
        <node cat="np" id="7" rel="obj1">
          <node id="8" infl="geen" pos="det" rel="det" root="geen" sense="geen" wh="nwh"/>
          <node aform="base" id="9" infl="no_e" pos="adj" rel="mod" root="blind" sense="blind" vform="adj"/>
          <node gen="het" id="10" num="sg" pos="noun" rel="hd" root="geloof" sense="geloof"/>
          <node cat="pp" id="11" rel="mod">
            <node id="12" pos="prep" rel="hd" root="in" sense="in"/>
            <node id="13" neclass="PER" num="both" pos="name" rel="obj1" root="Christus" sense="Christus"/>
          </node>
        </node>
      </node>
    </node>
  </node>
</alpino_adt>
